CHANGELOG.md
docs/linguee-api.png
linguee_api/__init__.py
linguee_api/api.py
linguee_api/config.py
linguee_api/const.py
linguee_api/downloaders/__init__.py
linguee_api/downloaders/error_downloader.py
linguee_api/downloaders/file_cache.py
linguee_api/downloaders/httpx_downloader.py
linguee_api/downloaders/interfaces.py
linguee_api/downloaders/memory_cache.py
linguee_api/linguee_client.py
linguee_api/models.py
linguee_api/parser_utils.py
linguee_api/parsers.py
linguee_api/utils.py
linguee_api-2.5.1.dist-info/LICENSE
linguee_api-2.5.1.dist-info/WHEEL
linguee_api-2.5.1.dist-info/METADATA
linguee_api-2.5.1.dist-info/RECORD
