Metadata-Version: 2.1
Name: linguee-api
Version: 2.5.1
Summary: Linguee API
Home-page: https://github.com/imankulov/linguee-api
License: MIT
Author: Roman Imankulov
Author-email: roman.imankulov@gmail.com
Requires-Python: >=3.8,<4.0
Classifier: Intended Audience :: Developers
Classifier: License :: OSI Approved :: MIT License
Classifier: Programming Language :: Python :: 3
Classifier: Programming Language :: Python :: 3.10
Classifier: Programming Language :: Python :: 3.8
Classifier: Programming Language :: Python :: 3.9
Requires-Dist: fastapi (>=0.65.2,<0.66.0)
Requires-Dist: httpx (==1.0.0b0)
Requires-Dist: loguru (>=0.5.3,<0.6.0)
Requires-Dist: pydantic (>=1.8.1,<2.0.0)
Requires-Dist: python-dotenv (>=0.17.0,<0.18.0)
Requires-Dist: sentry-sdk (>=1.0.0,<2.0.0)
Requires-Dist: uvicorn (>=0.13.4,<0.14.0)
Requires-Dist: xextract (>=0.1.8,<0.2.0)
Project-URL: Repository, https://github.com/imankulov/linguee-api
